quart_trio-0.12.0.dist-info/METADATA
quart_trio-0.12.0.dist-info/WHEEL
quart_trio-0.12.0.dist-info/entry_points.txt
quart_trio-0.12.0.dist-info/licenses/LICENSE
quart_trio/__init__.py
quart_trio/app.py
quart_trio/asgi.py
quart_trio/datastructures.py
quart_trio/formparser.py
quart_trio/py.typed
quart_trio/testing/__init__.py
quart_trio/testing/app.py
quart_trio/testing/client.py
quart_trio/testing/connections.py
quart_trio/utils.py
quart_trio/wrappers/__init__.py
quart_trio/wrappers/request.py
quart_trio/wrappers/response.py
quart_trio/wrappers/websocket.py
quart_trio-0.12.0.dist-info/RECORD
