Metadata-Version: 2.1
Name: quart-trio
Version: 0.12.0
Summary: A Quart extension to provide trio support
Author-Email: pgjones <philip.graham.jones@googlemail.com>
License: MIT
Classifier: Development Status :: 3 - Alpha
Classifier: Environment :: Web Environment
Classifier: Intended Audience :: Developers
Classifier: License :: OSI Approved :: MIT License
Classifier: Operating System :: OS Independent
Classifier: Programming Language :: Python
Classifier: Programming Language :: Python :: 3
Classifier: Programming Language :: Python :: 3.9
Classifier: Programming Language :: Python :: 3.10
Classifier: Programming Language :: Python :: 3.11
Classifier: Programming Language :: Python :: 3.12
Classifier: Programming Language :: Python :: 3.13
Classifier: Topic :: Internet :: WWW/HTTP :: Dynamic Content
Classifier: Topic :: Software Development :: Libraries :: Python Modules
Requires-Python: >=3.9
Requires-Dist: exceptiongroup>=1.1.0; python_version < "3.11"
Requires-Dist: hypercorn[trio]>=0.12.0
Requires-Dist: quart>=0.19
Requires-Dist: trio>=0.19.0
Provides-Extra: docs
Requires-Dist: pydata_sphinx_theme; extra == "docs"
